bos_mint/VERSION
bos_mint/__init__.py
bos_mint/assets.py
bos_mint/cli.py
bos_mint/config-defaults.yaml
bos_mint/datestring.py
bos_mint/forms.py
bos_mint/istring.py
bos_mint/menu_info.py
bos_mint/models.py
bos_mint/node.py
bos_mint/tostring.py
bos_mint/utils.py
bos_mint/views.py
bos_mint/web.py
bos_mint/widgets.py
bos_mint/wrapper.py
bos_mint/dataproxy_link/__init__.py
bos_mint/dataproxy_link/control.py
bos_mint/dataproxy_link/ping.py
bos_mint/static/favicon.ico
bos_mint/static/css/img-modal.css
bos_mint/static/css/libs.css
bos_mint/static/css/main.css
bos_mint/static/css/src/styles.css
bos_mint/static/fonts/FontAwesome.otf
bos_mint/static/fonts/basic.icons.eot
bos_mint/static/fonts/basic.icons.svg
bos_mint/static/fonts/basic.icons.ttf
bos_mint/static/fonts/basic.icons.woff
bos_mint/static/fonts/fontawesome-webfont.eot
bos_mint/static/fonts/fontawesome-webfont.svg
bos_mint/static/fonts/fontawesome-webfont.ttf
bos_mint/static/fonts/fontawesome-webfont.woff
bos_mint/static/fonts/fontawesome-webfont.woff2
bos_mint/static/fonts/icons.eot
bos_mint/static/fonts/icons.otf
bos_mint/static/fonts/icons.svg
bos_mint/static/fonts/icons.ttf
bos_mint/static/fonts/icons.woff
bos_mint/static/img/glyphicons-halflings-white.png
bos_mint/static/img/glyphicons-halflings.png
bos_mint/static/img/logo.png
bos_mint/static/img/help/bettingmarket.png
bos_mint/static/img/help/bettingmarketgroup.png
bos_mint/static/img/help/event.png
bos_mint/static/img/help/event_status.png
bos_mint/static/js/img-modal.js
bos_mint/static/js/src/main.js
bos_mint/static/webassets-external/0b62c6c2ec5417e8167217b8a31592e3_font-awesome.min.css
bos_mint/static/webassets-external/0fd1f80dee7074b3d826491105ebe0f7_semantic.min.css
bos_mint/static/webassets-external/21d9e91cbdd9b37c70f5fc10d9cfe808_jquery.min.js
bos_mint/static/webassets-external/35dab832d85b2d1bdd94a832f62e8abe_icons.woff2
bos_mint/static/webassets-external/459dd135b89243dc05c204ba0ba5795e_semantic.min.js
bos_mint-0.5.2.dist-info/LICENSE.txt
bos_mint-0.5.2.dist-info/METADATA
bos_mint-0.5.2.dist-info/WHEEL
bos_mint-0.5.2.dist-info/entry_points.txt
bos_mint-0.5.2.dist-info/top_level.txt
bos_mint-0.5.2.dist-info/RECORD
