Metadata-Version: 2.1
Name: bos-mint
Version: 0.5.2
Summary: BOS Manual intervention module for PeerPlays
Home-page: http://pbsa.info
Author: Peerplays Community
Maintainer: Peerplays Community
License: UNKNOWN
Download-URL: https://github.com/pbsa/bos-mint/tarball/0.5.2
Keywords: peerplays,bos
Platform: UNKNOWN
Classifier: License :: OSI Approved :: GNU General Public License v3 (GPLv3)
Classifier: Operating System :: OS Independent
Classifier: Programming Language :: Python :: 3
Classifier: Development Status :: 3 - Alpha
Classifier: Intended Audience :: Developers
Requires-Dist: graphenelib (>=1.0.1)
Requires-Dist: peerplays (>=0.3.0)
Requires-Dist: bookiesports
Requires-Dist: bos-incidents
Requires-Dist: bos-sync (>=0.3.0)
Requires-Dist: pytz
Requires-Dist: Flask
Requires-Dist: Flask-Assets
Requires-Dist: Flask-Mail
Requires-Dist: Flask-Markdown
Requires-Dist: Flask-WTF
Requires-Dist: Jinja2
Requires-Dist: Markdown
Requires-Dist: PyYAML
Requires-Dist: requests
Requires-Dist: webassets (>=0-12.1)
Requires-Dist: flask-script
Requires-Dist: flask-sqlalchemy
Requires-Dist: mysqlclient
Requires-Dist: SQLAlchemy
Requires-Dist: uwsgi
Requires-Dist: strict-rfc3339
Requires-Dist: email-validator
